MANIFEST.in
README.markdown
setup.py
convert_to_redirects.egg-info/PKG-INFO
convert_to_redirects.egg-info/SOURCES.txt
convert_to_redirects.egg-info/dependency_links.txt
convert_to_redirects.egg-info/entry_points.txt
convert_to_redirects.egg-info/requires.txt
convert_to_redirects.egg-info/top_level.txt
redirects/__init__.py
redirects/redirects.py